{"_state_version":1,"_state_engine_version":4,"_local":{"first_run":false,"initial_cwd":"/workspaces/CamOnAirFlow","_last_extracted_at":"2026-04-16T07:07:19.320855+00:00","_last_extracted_hash":"N08pqgEVpgTJvOaik4Lp2MKpFWZRxLXsa6js5MMtR20="},"schema_names":["japan_jma_source"],"default_schema_name":"japan_jma_source","pipeline_name":"japan_jma_weather_pipeline","dataset_name":"weather_jp","destination_type":"dlt.destinations.motherduck","destination_name":null,"_version_hash":"N08pqgEVpgTJvOaik4Lp2MKpFWZRxLXsa6js5MMtR20=","sources":{"japan_jma_source":{"japan_jma_weather":{"Daily_Requests":{"2026-04-16":39},"Processed_Ranges":{"Kiroro Resort":[{"request_year":"2024","start_date":"2023-11-01","end_date":"2024-04-30","loaded_at":"2026-04-16T07:05:30.114568+00:00"},{"request_year":"2025","start_date":"2024-11-01","end_date":"2025-04-30","loaded_at":"2026-04-16T07:05:33.541600+00:00"},{"request_year":"2026","start_date":"2025-11-01","end_date":"2026-04-14","loaded_at":"2026-04-16T07:05:37.065119+00:00"}],"Rusutsu Resort Ski Area":[{"request_year":"2024","start_date":"2023-11-01","end_date":"2024-04-30","loaded_at":"2026-04-16T07:05:39.588995+00:00"},{"request_year":"2025","start_date":"2024-11-01","end_date":"2025-04-30","loaded_at":"2026-04-16T07:05:42.091168+00:00"},{"request_year":"2026","start_date":"2025-11-01","end_date":"2026-04-14","loaded_at":"2026-04-16T07:05:44.579642+00:00"}],"Mount Racey":[{"request_year":"2024","start_date":"2023-11-01","end_date":"2024-04-30","loaded_at":"2026-04-16T07:05:47.071043+00:00"},{"request_year":"2025","start_date":"2024-11-01","end_date":"2025-04-30","loaded_at":"2026-04-16T07:05:50.372341+00:00"},{"request_year":"2026","start_date":"2025-11-01","end_date":"2026-04-14","loaded_at":"2026-04-16T07:05:53.232114+00:00"}],"Niseko United":[{"request_year":"2024","start_date":"2023-11-01","end_date":"2024-04-30","loaded_at":"2026-04-16T07:05:56.931409+00:00"},{"request_year":"2025","start_date":"2024-11-01","end_date":"2025-04-30","loaded_at":"2026-04-16T07:06:00.451878+00:00"},{"request_year":"2026","start_date":"2025-11-01","end_date":"2026-04-14","loaded_at":"2026-04-16T07:06:04.412512+00:00"}],"Furano Ski Resort":[{"request_year":"2024","start_date":"2023-11-01","end_date":"2024-04-30","loaded_at":"2026-04-16T07:06:07.296199+00:00"},{"request_year":"2025","start_date":"2024-11-01","end_date":"2025-04-30","loaded_at":"2026-04-16T07:06:10.166583+00:00"},{"request_year":"2026","start_date":"2025-11-01","end_date":"2026-04-14","loaded_at":"2026-04-16T07:06:12.634909+00:00"}],"Tomamu Ski Resort":[{"request_year":"2024","start_date":"2023-11-01","end_date":"2024-04-30","loaded_at":"2026-04-16T07:06:15.123973+00:00"},{"request_year":"2025","start_date":"2024-11-01","end_date":"2025-04-30","loaded_at":"2026-04-16T07:06:17.627941+00:00"},{"request_year":"2026","start_date":"2025-11-01","end_date":"2026-04-14","loaded_at":"2026-04-16T07:06:20.087759+00:00"}],"Hakodate Nanae Snowpark":[{"request_year":"2024","start_date":"2023-11-01","end_date":"2024-04-30","loaded_at":"2026-04-16T07:06:23.541141+00:00"},{"request_year":"2025","start_date":"2024-11-01","end_date":"2025-04-30","loaded_at":"2026-04-16T07:06:27.322862+00:00"},{"request_year":"2026","start_date":"2025-11-01","end_date":"2026-04-14","loaded_at":"2026-04-16T07:06:30.726128+00:00"}],"Sahoro":[{"request_year":"2024","start_date":"2023-11-01","end_date":"2024-04-30","loaded_at":"2026-04-16T07:06:33.250454+00:00"},{"request_year":"2025","start_date":"2024-11-01","end_date":"2025-04-30","loaded_at":"2026-04-16T07:06:35.769193+00:00"},{"request_year":"2026","start_date":"2025-11-01","end_date":"2026-04-14","loaded_at":"2026-04-16T07:06:38.616748+00:00"}],"Appi Kogen Ski Resort":[{"request_year":"2024","start_date":"2023-11-01","end_date":"2024-04-30","loaded_at":"2026-04-16T07:06:41.107135+00:00"},{"request_year":"2025","start_date":"2024-11-01","end_date":"2025-04-30","loaded_at":"2026-04-16T07:06:43.496562+00:00"},{"request_year":"2026","start_date":"2025-11-01","end_date":"2026-04-14","loaded_at":"2026-04-16T07:06:45.932292+00:00"}],"Shizukuishi Ski Resort":[{"request_year":"2024","start_date":"2023-11-01","end_date":"2024-04-30","loaded_at":"2026-04-16T07:06:48.374000+00:00"},{"request_year":"2025","start_date":"2024-11-01","end_date":"2025-04-30","loaded_at":"2026-04-16T07:06:50.838497+00:00"},{"request_year":"2026","start_date":"2025-11-01","end_date":"2026-04-14","loaded_at":"2026-04-16T07:06:53.320758+00:00"}],"Takasu Snow Park":[{"request_year":"2024","start_date":"2023-11-01","end_date":"2024-04-30","loaded_at":"2026-04-16T07:06:55.823131+00:00"},{"request_year":"2025","start_date":"2024-11-01","end_date":"2025-04-30","loaded_at":"2026-04-16T07:06:58.324852+00:00"},{"request_year":"2026","start_date":"2025-11-01","end_date":"2026-04-14","loaded_at":"2026-04-16T07:07:00.847579+00:00"}],"Zao Onsen Ski Resort":[{"request_year":"2024","start_date":"2023-11-01","end_date":"2024-04-30","loaded_at":"2026-04-16T07:07:04.212016+00:00"},{"request_year":"2025","start_date":"2024-11-01","end_date":"2025-04-30","loaded_at":"2026-04-16T07:07:07.620170+00:00"},{"request_year":"2026","start_date":"2025-11-01","end_date":"2026-04-14","loaded_at":"2026-04-16T07:07:11.344944+00:00"}],"Miyagi Zao Eboshi Resort":[{"request_year":"2024","start_date":"2023-11-01","end_date":"2024-04-30","loaded_at":"2026-04-16T07:07:13.968504+00:00"},{"request_year":"2025","start_date":"2024-11-01","end_date":"2025-04-30","loaded_at":"2026-04-16T07:07:16.418316+00:00"},{"request_year":"2026","start_date":"2025-11-01","end_date":"2026-04-14","loaded_at":"2026-04-16T07:07:18.924576+00:00"}]},"Daily_default":{"2026-04-16":false}}}}}